MANIFEST.in
README.md
setup.py
requirements/dev.txt
requirements/install.txt
skeppa/__init__.py
skeppa/api.py
skeppa/main.py
skeppa/settings.py
skeppa.egg-info/PKG-INFO
skeppa.egg-info/SOURCES.txt
skeppa.egg-info/dependency_links.txt
skeppa.egg-info/entry_points.txt
skeppa.egg-info/not-zip-safe
skeppa.egg-info/requires.txt
skeppa.egg-info/top_level.txt
skeppa/ext/__init__.py
skeppa/ext/ecr.py
skeppa/scripts/__init__.py
skeppa/scripts/skeppa.py
skeppa/utils/__init__.py
skeppa/utils/dockerfile.py