Metadata-Version: 1.1
Name: skeppa
Version: 1.1.0
Summary: UNKNOWN
Home-page: https://github.com/marteinn/skeppa
Author: Marteinn
Author-email: martin@marteinn.se
License: MIT
Platform: UNKNOWN
Classifier: Development Status :: 5 - Production/Stable
Classifier: Environment :: Console
Classifier: Environment :: Web Environment
Classifier: Intended Audience :: Developers
Classifier: Intended Audience :: System Administrators
Classifier: Natural Language :: English
Classifier: License :: OSI Approved :: MIT License
Classifier: Programming Language :: Python
Classifier: Programming Language :: Python :: 2
Classifier: Programming Language :: Python :: 2.7
Classifier: Topic :: Software Development :: Build Tools
Classifier: Topic :: Software Development :: Libraries
Classifier: Topic :: System :: Software Distribution
Classifier: Topic :: System :: Systems Administration
